{"data":[{"title":"(SPONSO) Présentation/Découverte - Endless Space 2","url":"/watch?v=bs63PGiMIWU"},{"title":"FAQ du Bazar !","url":"/watch?v=0ervEOoHPHM"},{"title":"Aventures Live \"Progénitures\" (02/09/16) Invité : LinkstheSun - Fin","url":"/watch?v=yD0WP_eudFQ"},{"title":"Les Survivants - Episode 2 - Road Rage","url":"/watch?v=w_G6ZstA_oA"},{"title":"Le jeu à 10 Balles (let's play)  - GrowUp","url":"/watch?v=cnUJZ3SH6Ps"},{"title":"Moi, Président - Let's play Narratif - Episode 4","url":"/watch?v=t1Goq5qih0I"},{"title":"ANNONCE MAGICAL AVENTURES","url":"/watch?v=TI1H5i16Wf0"},{"title":"Les Survivants  - Episode 1 -  First Blood","url":"/watch?v=7YgkMxyj1cc"},{"title":"JEU EN VRAC - Jeux éducatifs !","url":"/watch?v=9jsEqvBbDsY"},{"title":"Aventures Live \"Progénitures\" (02/09/16) Invité : LinkstheSun - Partie 3","url":"/watch?v=xYLhdsE9i2Q"},{"title":"Let's Play de la PEUR ! - The Visitor","url":"/watch?v=mupnsVgsUDA"},{"title":"Moi, Président - Let's play Narratif - Episode 3","url":"/watch?v=yejWwdC99s8"},{"title":"LES SURVIVANTS - Episode 0 - Explication des règles et choix des persos","url":"/watch?v=OheEVaoNrK0"},{"title":"JDG la Revanche - Fantasia - Episode 2","url":"/watch?v=t3sPsK4yXX8"},{"title":"Aventures Live \"Progénitures\" (02/09/16) Invité : LinkstheSun - Partie 2","url":"/watch?v=aBMub2UE9Ho"},{"title":"Batman the Telltale serie - Episode 4 - La violence c'est fantastique !","url":"/watch?v=GqV1h-w2p5E"},{"title":"Découverte - MOTHER RUSSIA BLEEDS","url":"/watch?v=Rg8hpXfdz4Y"},{"title":"Moi, Président - Let's play Narratif - Episode 2","url":"/watch?v=S5lo1hey1lU"},{"title":"Aventures Live \"Progénitures\" (02/09/16) Invité : LinkstheSun - Partie 1","url":"/watch?v=7MMRmr_LSLE"},{"title":"Aventures Live \"Ce ne sont pas des biscuits secs !\" - (30/07/2016) - FIN","url":"/watch?v=lK8Yg2p4Rg4"},{"title":"Aventures Saison 3 # 36 Fin (Dernière partie)","url":"/watch?v=s9M8sajsiKo"},{"title":"Punisher EP 10 - Cameos à GOGO !","url":"/watch?v=AJZgJ9_SvDg"},{"title":"Moi, Président - Let's play Narratif - Episode 1","url":"/watch?v=DRp-SVoBzRI"},{"title":"OVERSCHNAPS sur OVERWATCH avec Sorina, Benzaie & Bob Lennon","url":"/watch?v=4ImLArqC-SU"},{"title":"Aventures Live \"Ce ne sont pas des biscuits secs !\" - (30/07/2016) - Partie 4","url":"/watch?v=me6Jx6r-XhY"},{"title":"Aventures Saison 3 # 35 Fin (1ère partie)","url":"/watch?v=PvfQmrV9hJ0"},{"title":"Batman The telltale Serie -  Episode 3 - PandaWoman","url":"/watch?v=351mpZcp_0E"},{"title":"Découverte - Attack on Titan Wings of Freedom","url":"/watch?v=qollYQi-P8k"},{"title":"Retro-découverte - Close Combat","url":"/watch?v=LtqSn8w2ik8"},{"title":"Annonce fraîche !!! (Live d'Aventures 2 septembre avec un invité)","url":"/watch?v=k8e7GgLD75s"}]}
